demeter_dl/Core.py
demeter_dl/Helper.py
demeter_dl/__init__.py
demeter_dl/__main__.py
demeter_dl/__version__.py
demeter_dl/mixer.py
Demeter_Dl-1.0.1.dist-info/LICENSE
Demeter_Dl-1.0.1.dist-info/METADATA
Demeter_Dl-1.0.1.dist-info/WHEEL
Demeter_Dl-1.0.1.dist-info/top_level.txt
Demeter_Dl-1.0.1.dist-info/RECORD
