Metadata-Version: 2.1
Name: Demeter-Dl
Version: 1.0.1
Summary: A Simple Downloader
Home-page: https://github.com/liupold/demeter_dl
Author: RohnCh(Liupold)
Author-email: rohn.ch@gmail.com
License: UNKNOWN
Keywords: Downloader youtube demeter efficient Download
Platform: UNKNOWN
Classifier: Programming Language :: Python :: 3.4
Classifier: Programming Language :: Python :: 3.5
Classifier: Programming Language :: Python :: 3.6
Classifier: Programming Language :: Python :: 3.7
Classifier: License :: OSI Approved :: GNU Lesser General Public License v3 or later (LGPLv3+)
Classifier: Operating System :: OS Independent
Requires-Python: >=3.4
Requires-Dist: requests
Requires-Dist: colorama
Requires-Dist: pafy
Requires-Dist: youtube-dl
Requires-Dist: click
Requires-Dist: tqdm
Requires-Dist: ffmpy
